CONTRIBUTING.md
LICENSE
MANIFEST.in
README.md
README.rst
README.txt
requirements-dev.txt
requirements.txt
setup.py
Pulla.egg-info/PKG-INFO
Pulla.egg-info/SOURCES.txt
Pulla.egg-info/dependency_links.txt
Pulla.egg-info/entry_points.txt
Pulla.egg-info/requires.txt
Pulla.egg-info/top_level.txt
docs/README.md
pulla/__init__.py
pulla/logger.py
pulla/main.py
pulla/pulla.py
pulla/utils.py
tests/test_logger.py
tests/test_main.py
tests/test_pulla.py
tests/test_utils.py