Metadata-Version: 2.1
Name: Pulla
Version: 0.3.0
Summary: Pulla helps you pull content from all repos in any folder
Home-page: https://github.com/ylogx/pulla
Author: Shubham Chaudhary
Author-email: shubham@chaudhary.xyz
License: GPLv3+
License-File: LICENSE
Requires-Dist: colorama==0.4.6
